Pendu/__main__.py
pendu-0.1.0.dist-info/WHEEL
pendu-0.1.0.dist-info/METADATA
pendu-0.1.0.dist-info/RECORD
